homomorph/__init__.py
homomorph/hmm.py
homomorph-0.3.0.dist-info/LICENSE.txt
homomorph-0.3.0.dist-info/METADATA
homomorph-0.3.0.dist-info/WHEEL
homomorph-0.3.0.dist-info/top_level.txt
homomorph-0.3.0.dist-info/RECORD
