Metadata-Version: 2.1
Name: homomorph
Version: 0.3.0
Summary: A numerically stable implementation of essential HMM algorithms with tutorials on training methods
Home-page: https://github.com/marcsingleton/homomorph
Author: Marc Singleton
Author-email: marcsingleton@berkeley.edu
Classifier: Programming Language :: Python :: 3
Classifier: License :: OSI Approved :: MIT License
Classifier: Operating System :: OS Independent
Requires-Python: >=3.8
License-File: LICENSE.txt
Requires-Dist: numpy (>=1.17)
Requires-Dist: scipy (>=1.9)
